{
"type": "FeatureCollection",
"name": "selected_sites",
"crs": { "type": "name", "properties": { "name": "urn:ogc:def:crs:OGC:1.3:CRS84" } },
"features": [
{ "type": "Feature", "properties": { "cand_id": "C00420", "demand_score": 0.084641638225255986, "selected": true, "p_off": 0.050110210914911302, "p_mid": 0.05000856148461677, "p_peak": 0.050070402330895269, "profit": -7.2509225251963416, "consumer_cost": 5.1904375703706576, "rerouting": 0.0 }, "geometry": { "type": "Point", "coordinates": [ 117.282814478906801, 31.865678105999987 ] } },
{ "type": "Feature", "properties": { "cand_id": "C00423", "demand_score": 0.6013651877133106, "selected": true, "p_off": 0.050236313494868678, "p_mid": 0.050568407075479604, "p_peak": 0.05085851302401509, "profit": -51.123973620435493, "consumer_cost": 37.216696326460024, "rerouting": 0.0 }, "geometry": { "type": "Point", "coordinates": [ 117.898798606905046, 31.626985336797979 ] } },
{ "type": "Feature", "properties": { "cand_id": "C00499", "demand_score": 0.07781569965870308, "selected": true, "p_off": 0.050079262800842253, "p_mid": 0.051415011627371943, "p_peak": 0.051426509540142801, "profit": -6.572091505820655, "consumer_cost": 4.8531793731257196, "rerouting": 0.0 }, "geometry": { "type": "Point", "coordinates": [ 117.254692589284247, 31.841080194099977 ] } },
{ "type": "Feature", "properties": { "cand_id": "C00514", "demand_score": 0.4, "selected": true, "p_off": 0.050777428220581039, "p_mid": 0.050051579591829751, "p_peak": 0.050518233672113333, "profit": -34.061264300990658, "consumer_cost": 24.706401903380765, "rerouting": 0.0 }, "geometry": { "type": "Point", "coordinates": [ 117.640300714507617, 31.803894091749363 ] } },
{ "type": "Feature", "properties": { "cand_id": "C00517", "demand_score": 0.4, "selected": true, "p_off": 0.050102866163934154, "p_mid": 0.053993420071647091, "p_peak": 0.050521769393473706, "profit": -33.484310847504169, "consumer_cost": 25.204855817398503, "rerouting": 0.0 }, "geometry": { "type": "Point", "coordinates": [ 117.640279850000283, 31.803907800002786 ] } },
{ "type": "Feature", "properties": { "cand_id": "C00524", "demand_score": 0.4, "selected": true, "p_off": 0.050297686371872916, "p_mid": 0.056944707147772125, "p_peak": 0.050226328865899769, "profit": -32.985220323490026, "consumer_cost": 25.635530339256896, "rerouting": 0.0 }, "geometry": { "type": "Point", "coordinates": [ 117.6399200500002, 31.804026550002618 ] } },
{ "type": "Feature", "properties": { "cand_id": "C00534", "demand_score": 0.079180887372013661, "selected": true, "p_off": 0.050201157758981235, "p_mid": 0.050004493768415502, "p_peak": 0.050197701535703035, "profit": -6.7756051273488245, "consumer_cost": 4.8620690451295543, "rerouting": 0.0 }, "geometry": { "type": "Point", "coordinates": [ 117.253967500000016, 31.8404267 ] } },
{ "type": "Feature", "properties": { "cand_id": "C00537", "demand_score": 0.4, "selected": true, "p_off": 0.050287166332352411, "p_mid": 0.080067768347692969, "p_peak": 0.050007595831160712, "profit": -29.096541899134706, "consumer_cost": 28.974757368596343, "rerouting": 0.0 }, "geometry": { "type": "Point", "coordinates": [ 117.639878050000235, 31.804054100002606 ] } },
{ "type": "Feature", "properties": { "cand_id": "C00582", "demand_score": 0.4, "selected": true, "p_off": 0.051432761547118885, "p_mid": 0.050167270803786114, "p_peak": 0.05930491527081494, "profit": -32.383921735088947, "consumer_cost": 26.154359521989772, "rerouting": 0.0 }, "geometry": { "type": "Point", "coordinates": [ 117.640436600000271, 31.804043900002736 ] } },
{ "type": "Feature", "properties": { "cand_id": "C00596", "demand_score": 0.10375426621160409, "selected": true, "p_off": 0.051728002090136491, "p_mid": 0.050107018248215326, "p_peak": 0.050763123712027, "profit": -8.7776053227793351, "consumer_cost": 6.4580976985589178, "rerouting": 0.0 }, "geometry": { "type": "Point", "coordinates": [ 117.249858014960822, 31.840096002678091 ] } }
]
}
